yatter/__init__.py
yatter/__main__.py
yatter/cli.py
yatter/constants.py
yatter/function.py
yatter/graph.py
yatter/mapping.py
yatter/normalization.py
yatter/predicateobject.py
yatter/source.py
yatter/subject.py
yatter/target.py
yatter/termmap.py
yatter-2.0.3.dist-info/METADATA
yatter-2.0.3.dist-info/WHEEL
yatter-2.0.3.dist-info/entry_points.txt
yatter-2.0.3.dist-info/licenses/LICENSE
yatter-2.0.3.dist-info/RECORD
