Metadata-Version: 2.4
Name: yatter
Version: 2.0.3
Summary: The tool translates mapping rules from YARRRML in a turtle-based serialization of RML or R2RML.
License: Apache License
License-File: LICENSE
Author: David Chaves
Author-email: david.chaves@usc.es
Requires-Python: >=3.9,<4.0
Classifier: License :: Other/Proprietary License
Classifier: Programming Language :: Python :: 3
Classifier: Programming Language :: Python :: 3.9
Classifier: Programming Language :: Python :: 3.10
Classifier: Programming Language :: Python :: 3.11
Classifier: Programming Language :: Python :: 3.12
Classifier: Programming Language :: Python :: 3.13
Classifier: Programming Language :: Python :: 3.14
Requires-Dist: coloredlogs (>=15.0.1,<16.0.0)
Requires-Dist: pyjelly (>=0.6.1)
Requires-Dist: rdflib (>=7.1.1,<8.0.0)
Requires-Dist: ruamel-yaml (>=0.18.10,<0.19.0)
